choosi/__init__.py
choosi/example.py
choosi-0.0.0.dist-info/LICENSE
choosi-0.0.0.dist-info/METADATA
choosi-0.0.0.dist-info/WHEEL
choosi-0.0.0.dist-info/RECORD
